aws_consoler/__init__.py
aws_consoler/cli.py
aws_consoler/logic.py
aws_consoler-1.1.0.dist-info/AUTHORS.rst
aws_consoler-1.1.0.dist-info/LICENSE
aws_consoler-1.1.0.dist-info/METADATA
aws_consoler-1.1.0.dist-info/WHEEL
aws_consoler-1.1.0.dist-info/entry_points.txt
aws_consoler-1.1.0.dist-info/top_level.txt
aws_consoler-1.1.0.dist-info/zip-safe
aws_consoler-1.1.0.dist-info/RECORD
